ssiaquitaine/__init__.py
ssiaquitaine/audit.py
ssiaquitaine/core.py
ssiaquitaine/planning.py
ssiaquitaine/reporting.py
ssiaquitaine/tasks.py
ssiaquitaine-0.1.2.dist-info/licenses/LICENSE
ssiaquitaine-0.1.2.dist-info/METADATA
ssiaquitaine-0.1.2.dist-info/WHEEL
ssiaquitaine-0.1.2.dist-info/entry_points.txt
ssiaquitaine-0.1.2.dist-info/top_level.txt
ssiaquitaine-0.1.2.dist-info/RECORD
