Metadata-Version: 2.4
Name: SSIaquitaine
Version: 0.1.2
Summary: Un outil de gestion de projet pour un SSI (Système de Sécurité Informatique).
Author-email: Mohamed Redha Abdessemed <mohamed.abdessemed@eurocybersecurite.fr>
Project-URL: Homepage, https://github.com/tuteur1/SSIaquitaine
Project-URL: Bug Tracker, https://github.com/tuteur1/SSIaquitaine/issues
Classifier: Programming Language :: Python :: 3
Classifier: License :: OSI Approved :: MIT License
Classifier: Operating System :: OS Independent
Classifier: Topic :: Security
Classifier: Topic :: Software Development :: Libraries :: Python Modules
Classifier: Framework :: Setuptools Plugin
Requires-Python: >=3.9
License-File: LICENSE
Requires-Dist: pytest
Requires-Dist: colorama
Dynamic: license-file
